font_generator/__init__.py
font_generator/__main__.py
font_generator/cli.py
font_generator/handwritten.py
font_generator/svg_to_ttf.py
font_generator/ttf_to_svg.py
font_generator-1.0.1.dist-info/licenses/LICENSE
font_generator-1.0.1.dist-info/METADATA
font_generator-1.0.1.dist-info/WHEEL
font_generator-1.0.1.dist-info/entry_points.txt
font_generator-1.0.1.dist-info/top_level.txt
font_generator-1.0.1.dist-info/RECORD
