Metadata-Version: 2.4
Name: font-generator
Version: 1.0.1
Summary: A Python package for font manipulation and conversion
Home-page: https://github.com/GenXLabs-org/font-generator
Author: GenXLabs.org
Author-email: "GenXLabs.org" <genxlabs385@outlook.com>
License-Expression: MIT
Project-URL: Homepage, https://github.com/GenXLabs-org/font-generator
Project-URL: Documentation, https://github.com/GenXLabs-org/font-generator#readme
Project-URL: Repository, https://github.com/GenXLabs-org/font-generator
Project-URL: Issues, https://github.com/GenXLabs-org/font-generator/issues
Keywords: font,ttf,otf,svg,conversion,handwritten,typography
Classifier: Development Status :: 5 - Production/Stable
Classifier: Intended Audience :: Developers
Classifier: Topic :: Text Processing :: Fonts
Classifier: Programming Language :: Python :: 3
Classifier: Programming Language :: Python :: 3.7
Classifier: Programming Language :: Python :: 3.8
Classifier: Programming Language :: Python :: 3.9
Classifier: Programming Language :: Python :: 3.10
Classifier: Programming Language :: Python :: 3.11
Classifier: Programming Language :: Python :: 3.12
Requires-Python: >=3.7
License-File: LICENSE
Requires-Dist: fonttools>=4.0.0
Requires-Dist: svgpathtools>=1.4.0
Requires-Dist: tqdm>=4.60.0
Provides-Extra: handwritten
Requires-Dist: fontforge; extra == "handwritten"
Dynamic: author
Dynamic: home-page
Dynamic: license-file
Dynamic: requires-python
